sentry_feishu/__init__.py
sentry_feishu/forms.py
sentry_feishu/plugin.py
sentry_feishu_xrt/__init__.py
sentry_feishu_xrt/forms.py
sentry_feishu_xrt/plugin.py
sentry_feishu_xrt-0.0.6.dist-info/LICENSE
sentry_feishu_xrt-0.0.6.dist-info/METADATA
sentry_feishu_xrt-0.0.6.dist-info/WHEEL
sentry_feishu_xrt-0.0.6.dist-info/entry_points.txt
sentry_feishu_xrt-0.0.6.dist-info/top_level.txt
sentry_feishu_xrt-0.0.6.dist-info/RECORD
